{
    "data": [
        {
            "height": 0.3628996457628993,
            "time": "2025-07-28T19:17:00+00:00",
            "type": "high"
        },
        {
            "height": -0.2617221993832629,
            "time": "2025-07-29T02:13:00+00:00",
            "type": "low"
        },
        {
            "height": 0.47999657101088855,
            "time": "2025-07-29T07:11:00+00:00",
            "type": "high"
        },
        {
            "height": -0.45057376241087743,
            "time": "2025-07-29T14:37:00+00:00",
            "type": "low"
        },
        {
            "height": 0.34141475157446266,
            "time": "2025-07-29T19:48:00+00:00",
            "type": "high"
        },
        {
            "height": -0.2553194179519623,
            "time": "2025-07-30T02:47:00+00:00",
            "type": "low"
        },
        {
            "height": 0.4182842848791645,
            "time": "2025-07-30T07:51:00+00:00",
            "type": "high"
        },
        {
            "height": -0.3492652714288146,
            "time": "2025-07-30T15:14:00+00:00",
            "type": "low"
        },
        {
            "height": 0.29941653273539187,
            "time": "2025-07-30T20:21:00+00:00",
            "type": "high"
        },
        {
            "height": -0.2344999433610373,
            "time": "2025-07-31T03:26:00+00:00",
            "type": "low"
        },
        {
            "height": 0.32414274389106973,
            "time": "2025-07-31T08:33:00+00:00",
            "type": "high"
        },
        {
            "height": -0.24221805476963867,
            "time": "2025-07-31T15:55:00+00:00",
            "type": "low"
        },
        {
            "height": 0.23751889727429945,
            "time": "2025-07-31T20:57:00+00:00",
            "type": "high"
        },
        {
            "height": -0.20335768588775682,
            "time": "2025-08-01T04:17:00+00:00",
            "type": "low"
        },
        {
            "height": 0.21085639291821226,
            "time": "2025-08-01T09:22:00+00:00",
            "type": "high"
        },
        {
            "height": -0.13926249482923386,
            "time": "2025-08-01T16:52:00+00:00",
            "type": "low"
        },
        {
            "height": 0.1618995510088731,
            "time": "2025-08-01T21:39:00+00:00",
            "type": "high"
        },
        {
            "height": -0.17802552317429746,
            "time": "2025-08-02T05:31:00+00:00",
            "type": "low"
        },
        {
            "height": 0.10074165845784837,
            "time": "2025-08-02T10:36:00+00:00",
            "type": "high"
        },
        {
            "height": -0.0640057842362995,
            "time": "2025-08-02T18:23:00+00:00",
            "type": "low"
        }
    ],
    "meta": {
        "cost": 1,
        "dailyQuota": 10,
        "datum": "MSL",
        "end": "2025-08-02 19:00",
        "lat": -23.055,
        "lng": -43.535,
        "offset": 0,
        "requestCount": 3,
        "start": "2025-07-28 19:00",
        "station": {
            "distance": 51,
            "lat": -23,
            "lng": -44.03,
            "name": "ilha guaiba",
            "source": "sg"
        }
    }
}